tmrvirus/__init__.py
tmrvirus-1.0.0.dist-info/LICENSE
tmrvirus-1.0.0.dist-info/METADATA
tmrvirus-1.0.0.dist-info/WHEEL
tmrvirus-1.0.0.dist-info/top_level.txt
tmrvirus-1.0.0.dist-info/RECORD
