Metadata-Version: 2.1
Name: tmrvirus
Version: 1.0.0
Summary: Module Added To The Code Generated By Tmr Virus
Author-email: Tmr Virus <raofficialvirus@gmail.com>
Classifier: Programming Language :: Python :: 3
Classifier: License :: OSI Approved :: MIT License
Classifier: Operating System :: OS Independent
Requires-Python: >=3.8
License-File: LICENSE
